clidec/__init__.py
clidec-0.0.1.dist-info/LICENSE
clidec-0.0.1.dist-info/METADATA
clidec-0.0.1.dist-info/WHEEL
clidec-0.0.1.dist-info/top_level.txt
clidec-0.0.1.dist-info/RECORD
