Metadata-Version: 2.1
Name: clidec
Version: 0.0.1
Summary: Build command line tools with sub-commands using decorators.
Home-page: https://github.com/urso/clidec
Author: Steffen Siering
License: UNKNOWN
Platform: UNKNOWN
